tests/__init__.py
tests/test.py
tests/integration/__init__.py
tests/integration/test_example_project_creation.py
tests/unit/__init__.py
tests/unit/test_main_window.py
tests/unit/test_matrix_data_conversion.py
titania/__init__.py
titania/__main__.py
titania/QtGUI/__init__.py
titania/QtGUI/base_tab.py
titania/QtGUI/error_tab.py
titania/QtGUI/main_window.py
titania/common/__init__.py
titania/common/interface_tab.py
titania/common/titania_tab.py
titania/data/__init__.py
titania/data/data_core.py
titania/data/examplary_generated_data.py
titania/data/root_data.py
titania/example/__init__.py
titania/example/copy_template.py
titania/example/example_files_interior.py
titania/panels/__init__.py
titania/panels/main_control_panel.py
titania/plots/__init__.py
titania/plots/base_plot.py
titania/plots/histogram_plot.py
titania/plots/line_plot.py
titania/plots/root_plot.py
titania/resources/__init__.py
titania/resources/cern.gif
titania/resources/cern.png
titania/resources/main_window.css
titania/template/__init__.py
titania/template/config.py
titania/template/main.py
titania/template/data/__init__.py
titania/template/panels/__init__.py
titania/template/panels/control_panel.py
titania/template/plots/__init__.py
titania/template/views/__init__.py
titania/template/views/thresholds.py
titania/template/views/thresholds_gui.py
titania/web/__init__.py
titania/web/base_tab.py
titania/web/main_window.py
titania-0.3.71.dist-info/LICENSE
titania-0.3.71.dist-info/METADATA
titania-0.3.71.dist-info/WHEEL
titania-0.3.71.dist-info/top_level.txt
titania-0.3.71.dist-info/RECORD
