Metadata-Version: 2.1
Name: titania
Version: 0.3.71
Summary: Titania monitoring framework
Home-page: https://gitlab.com/mmajewsk/titania
Author: Maciej Majewski
Author-email: mmajewsk@cern.ch
License: UNKNOWN
Platform: UNKNOWN
Classifier: Programming Language :: Python :: 3
Classifier: Operating System :: OS Independent
License-File: LICENSE
Requires-Dist: Click (==7.1.2)
Requires-Dist: cycler (==0.10.0)
Requires-Dist: kiwisolver (==1.1.0)
Requires-Dist: matplotlib
Requires-Dist: numpy
Requires-Dist: pyparsing (==2.4.0)
Requires-Dist: PyQt5
Requires-Dist: PyQt5-sip
Requires-Dist: python-dateutil (==2.8.0)
Requires-Dist: python-dotenv (==0.10.1)
Requires-Dist: six (==1.12.0)
Requires-Dist: resources
Requires-Dist: jinja2
Requires-Dist: Flask (==1.1.1)
Requires-Dist: flask-nav
Requires-Dist: requests (~=2.25.1)
Requires-Dist: pandas (~=1.1.4)
Requires-Dist: mpld3 (~=0.5.2)
Requires-Dist: markupsafe (~=1.1.1)
Requires-Dist: setuptools (~=49.6.0)
Requires-Dist: pip (~=20.2.4)
